Workbook

Sheet 假設與參數
A1: VOXEN + 3CX 玉山 Outreach 案
A2: 3 年 / 5 年 TCO 對照試算表 · v1.0 · 2026-04-25
A4: ⚠ 內部使用 · 試算數字僅供討論 · 正式報價以 NDA 後為準
A6: ■ 藍字 = 可調整輸入 ■ 黑字 = 公式計算 ■ 綠字 = 跨工作表連結 黃底 = 關鍵假設
A8: 全域假設
A9: 座席數 | B9: 450 | C9: 席 | D9: 行外撥座席總數
A10: 評估年限 (3 年) | B10: 3 | C10: 年 | D10: Y1-Y3 短期 TCO 視角
A11: 評估年限 (5 年) | B11: 5 | C11: 年 | D11: Y1-Y5 長期 TCO 視角(含合約 evergreen)
A12: NTD/USD 匯率 | B12: 32.5 | D12: 依簽約日當週中央銀行匯率
A13: 折現率 (NPV 用) | B13: 0.04 | D13: 玉山內部資金成本參考
A14: 年通膨率 (人力) | B14: 0.03 | D14: 人力相關項目年增
A15: 年通膨率 (License) | B15: 0.02 | D15: 原廠 List Price 年增
A16: 時程風險加成 (自建) | B16: 0.2 | D16: 自建路徑時程超期 buffer 20%
A17: 時程風險加成 (Genesys 續用) | B17: 0.3 | D17: EOL 後 Extended Support 跳價 30%
A20: 方案 A: 續用 Genesys (Extended Support / Cloud 升級)
A21: Genesys Engage 11 Extended Support 年費 (USD) | B21: 380000 | C21: USD/年 | D21: EOL 後維護費,跳價 30% 以上
A22: Genesys Cloud per-Agent 月費 (USD) | B22: 95 | C22: USD/座席/月 | D22: 另一條路: 升 Cloud,Tier 3
A23: 遷移到 Cloud 一次性費用 (USD) | B23: 250000 | C23: USD | D23: 資料遷移 + 重新部署
A24: 原廠 PS 顧問 (Y1) | B24: 180000 | C24: USD | D24: EOL 補救方案的人月
A25: 玉山 IT 內部投入 (Y1) | B25: 120 | C25: 人月 | D25: 15% Genesys 知識轉移成本
A27: 方案 B: 瑛聲自建 PBX 平台 (替代方案)
A28: SIP/RTP/SBC 工程師 (人月成本) | B28: 280000 | C28: NTD/人月 | D28: 稀缺人才,含 fully loaded
A29: PM / 後端 / QA (人月成本) | B29: 200000 | C29: NTD/人月 | D29: 一般工程師 fully loaded
A30: 開發期人月需求 (高階 SIP) | B30: 18 | C30: 人月 | D30: 18 個月 × 1 senior FTE
A31: 開發期人月需求 (一般) | B31: 60 | C31: 人月 | D31: 18 個月 × 3.3 FTE 平均
A32: SBC 硬體一次性 (NTD) | B32: 1200000 | C32: NTD | D32: AudioCodes Mediant HA Pair
A33: Server 硬體一次性 (NTD) | B33: 800000 | C33: NTD | D33: 雙節點 + 監控 + 測試環境
A34: 第三方 codec/SBC license 年費 (NTD) | B34: 350000 | C34: NTD/年 | D34: G.729 / H.264 license
A35: 上線後維運團隊年薪 (NTD) | B35: 4800000 | C35: NTD/年 | D35: 2 FTE × 200K × 14 月 + 福利
A37: 方案 C: VOXEN + 3CX (瑛聲推薦) — Hybrid License Model
A38: 3CX PerSeat 永久授權 (核心 300 席, USD/席) | B38: 200 | C38: USD/席 永久 | D38: 一次性
A39: 3CX PerYear 訂閱 (彈性 150 席, USD/席/年) | B39: 60 | C39: USD/席/年 | D39: 年度可調
A40: 3CX Premium Partner 加成 (年, USD) | B40: 12000 | C40: USD/年 | D40: 原廠 escalation 升級
A41: Source Code Escrow 年費 (NTD) | B41: 80000 | C41: NTD/年 | D41: Iron Mountain 託管
A42: 瑛聲建置服務 (一次性, NTD) | B42: 2800000 | C42: NTD | D42: 6 個月開發 + 部署 + UAT
A43: 瑛聲年度維護 L1+L2 (NTD) | B43: 1800000 | C43: NTD/年 | D43: 7×24 支援 + 月度健診
A44: SBC 硬體 (一次性, NTD) | B44: 1200000 | C44: NTD | D44: AudioCodes (與自建同規格)
A45: OPEN/NAS 整合工時 (一次性 NTD) | B45: 600000 | C45: NTD | D45: 對接玉山既有資產

Sheet A.續用Genesys
A1: 方案 A — 續用 Genesys (NTD,千元)
A2: 前提:Genesys Engage 11 走 Extended Support 兩年,Y3 起被迫升級到 Genesys Cloud (per-agent 訂閱)。EOL 後 Extended Support 費用跳價 30%。
B4: Y0 (一次性) | C4: Y1 | D4: Y2 | E4: Y3 | F4: Y4 | G4: Y5
A5: Genesys Extended Support 年費 | B5: 0 | C5: =GEN_EXT*FX*(1+RISK_GENESYS) -> 16055000 | D5: =C5*(1+INFL_LICENSE) -> 16376100 | E5: 0 | F5: 0 | G5: 0
A6: Genesys Cloud 訂閱 (Y3 起切) | B6: 0 | C6: 0 | D6: 0 | E6: =GEN_CLOUD_PA*SEATS*12*FX -> 16672500 | F6: =E6*(1+INFL_LICENSE) -> 17005950 | G6: =F6*(1+INFL_LICENSE) -> 17346069
A7: 遷移到 Cloud 一次性 | B7: =GEN_MIGRATE*FX -> 8125000 | C7: 0 | D7: 0 | E7: 0 | F7: 0 | G7: 0
A8: 原廠 PS 顧問 (補救方案) | B8: 0 | C8: =GEN_PS*FX -> 5850000 | D8: 0 | E8: 0 | F8: 0 | G8: 0
A9: 玉山 IT 內部投入 | B9: 0 | C9: =GEN_INTERNAL_PM*BUILD_RATE_GEN -> 24000000 | D9: =C9*0.5*(1+INFL_LABOR) -> 12360000 | E9: =D9*(1+INFL_LABOR) -> 12730800 | F9: =E9*(1+INFL_LABOR) -> 13112724 | G9: =F9*(1+INFL_LABOR) -> 13506106
A10: 小計 (NTD) | B10: =SUM(B5:B9) -> 8125000 | C10: =SUM(C5:C9) -> 45905000 | D10: =SUM(D5:D9) -> 28736100 | E10: =SUM(E5:E9) -> 29403300 | F10: =SUM(F5:F9) -> 30118674 | G10: =SUM(G5:G9) -> 30852175
A11: 累積 TCO (NTD) | B11: =B10 -> 8125000 | C11: =B11+C10 -> 54030000 | D11: =C11+D10 -> 82766100 | E11: =D11+E10 -> 112169400 | F11: =E11+F10 -> 142288074 | G11: =F11+G10 -> 1.7314025e+08
A13: 3 年 TCO (Y0-Y3) | B13: =B10+C10+D10+E10 -> 112169400
A14: 5 年 TCO (Y0-Y5) | B14: =SUM(B10:G10) -> 1.7314025e+08
A15: 每席年成本 (5 年平均, NTD) | B15: =B14/SEATS/_YR5 -> 76951.222
A18: 【方案 A 風險提示】
A19: 1. EOL 後 Extended Support 是「賣方市場」,Genesys 可任意調價,30% 風險加成可能不夠
A20: 2. Y3 強制升級到 Cloud 後,客戶資料、客製流程需全部重做,有不可預期的工程量
A21: 3. Cloud 模式的「資料主權」議題 — 玉山法務可能不接受,可能再被迫換方案
A22: 4. 若 Y3 升級失敗或不滿意,Y3 之後可能還要再換廠商,5 年 TCO 可能再翻倍

Sheet B.自建
A1: 方案 B — 瑛聲自建 PBX 平台 (NTD,千元)
A2: 前提: 18 個月開發 + 6 個月測試,Y2-Q3 上線。Y1-Y2 為開發期,含 20% 時程超期 buffer。
B4: Y0 (一次性) | C4: Y1 | D4: Y2 | E4: Y3 | F4: Y4 | G4: Y5
A5: SIP/RTP/SBC 高階工程師 | B5: 0 | C5: =BUILD_RATE_SIP*BUILD_PM_SIP*0.4*(1+RISK_BUILD) -> 2419200 | D5: =BUILD_RATE_SIP*BUILD_PM_SIP*0.6*(1+RISK_BUILD)*(1+INFL_LABOR) -> 3737664 | E5: 0 | F5: 0 | G5: 0
A6: PM/後端/QA 一般工程師 | B6: 0 | C6: =BUILD_RATE_GEN*BUILD_PM_GEN*0.4*(1+RISK_BUILD) -> 5760000 | D6: =BUILD_RATE_GEN*BUILD_PM_GEN*0.6*(1+RISK_BUILD)*(1+INFL_LABOR) -> 8899200 | E6: 0 | F6: 0 | G6: 0
A7: SBC 硬體 (一次性) | B7: =BUILD_HW_SBC -> 1200000 | C7: 0 | D7: 0 | E7: 0 | F7: 0 | G7: 0
A8: Server 硬體 (一次性) | B8: =BUILD_HW_SRV -> 800000 | C8: 0 | D8: 0 | E8: 0 | F8: 0 | G8: 0
A9: 第三方 codec/license 年費 | B9: 0 | C9: =BUILD_3RD*0.5 -> 175000 | D9: =BUILD_3RD*(1+INFL_LICENSE) -> 357000 | E9: =D9*(1+INFL_LICENSE) -> 364140 | F9: =E9*(1+INFL_LICENSE) -> 371422.8 | G9: =F9*(1+INFL_LICENSE) -> 378851.26
A10: 上線後維運團隊 | B10: 0 | C10: 0 | D10: =BUILD_OPS*0.3 -> 1440000 | E10: =BUILD_OPS*(1+INFL_LABOR) -> 4944000 | F10: =E10*(1+INFL_LABOR) -> 5092320 | G10: =F10*(1+INFL_LABOR) -> 5245089.6
A11: 硬體年度維護 (15%) | B11: 0 | C11: 0 | D11: =(B7+B8)*0.15 -> 300000 | E11: =D11*(1+INFL_LICENSE) -> 306000 | F11: =E11*(1+INFL_LICENSE) -> 312120 | G11: =F11*(1+INFL_LICENSE) -> 318362.4
A12: 小計 (NTD) | B12: =SUM(B5:B11) -> 2000000 | C12: =SUM(C5:C11) -> 8354200 | D12: =SUM(D5:D11) -> 14733864 | E12: =SUM(E5:E11) -> 5614140 | F12: =SUM(F5:F11) -> 5775862.8 | G12: =SUM(G5:G11) -> 5942303.3
A13: 累積 TCO (NTD) | B13: =B12 -> 2000000 | C13: =B13+C12 -> 10354200 | D13: =C13+D12 -> 25088064 | E13: =D13+E12 -> 30702204 | F13: =E13+F12 -> 36478067 | G13: =F13+G12 -> 42420370
A15: 3 年 TCO (Y0-Y3) | B15: =B12+C12+D12+E12 -> 30702204
A16: 5 年 TCO (Y0-Y5) | B16: =SUM(B12:G12) -> 42420370
A17: 每席年成本 (5 年平均, NTD) | B17: =B16/SEATS/_YR5 -> 18853.498
A20: 【方案 B 風險提示】
A21: 1. SIP/RTP 高階工程師招募困難,實際人月成本可能比假設高 30-50%
A22: 2. 18 個月開發期是樂觀估計,業界實案常拉到 24-30 個月
A23: 3. 自建後玉山須長期承擔資安漏洞修補責任 — 一次大型漏洞可能讓 TCO 翻倍
A24: 4. Y2 上線後若有「上線失敗」或「無法達到 SLA」風險,可能需要 PBX vendor 救火 — 雙重支出
A25: 5. 此方案 5 年 TCO 通常是商業 PBX 方案的 2-3 倍,但帳上看起來「便宜」是因為許多 IT 投入不被計入

Sheet C.VOXEN+3CX
A1: 方案 C — VOXEN + 3CX (瑛聲推薦) (NTD,千元)
A2: 前提:Hybrid 授權 (核心 300 席 PerSeat 永久 + 彈性 150 席 PerYear)。建置 6 個月,Y1-Q3 即上線,Y2 起進入穩定維運。
B4: Y0 (一次性) | C4: Y1 | D4: Y2 | E4: Y3 | F4: Y4 | G4: Y5
A5: 3CX PerSeat 永久授權 (300 席) | B5: =VX_PERSEAT*300*FX -> 1950000 | C5: 0 | D5: 0 | E5: 0 | F5: 0 | G5: 0
A6: 3CX PerYear 訂閱 (150 席/年) | B6: 0 | C6: =VX_PERYEAR*150*FX -> 292500 | D6: =C6*(1+INFL_LICENSE) -> 298350 | E6: =D6*(1+INFL_LICENSE) -> 304317 | F6: =E6*(1+INFL_LICENSE) -> 310403.34 | G6: =F6*(1+INFL_LICENSE) -> 316611.41
A7: 3CX Premium Partner 加成 | B7: 0 | C7: =VX_PREM*FX -> 390000 | D7: =C7*(1+INFL_LICENSE) -> 397800 | E7: =D7*(1+INFL_LICENSE) -> 405756 | F7: =E7*(1+INFL_LICENSE) -> 413871.12 | G7: =F7*(1+INFL_LICENSE) -> 422148.54
A8: Source Code Escrow | B8: 0 | C8: =VX_ESCROW -> 80000 | D8: =C8*(1+INFL_LICENSE) -> 81600 | E8: =D8*(1+INFL_LICENSE) -> 83232 | F8: =E8*(1+INFL_LICENSE) -> 84896.64 | G8: =F8*(1+INFL_LICENSE) -> 86594.573
A9: 瑛聲建置服務 (一次性) | B9: =VX_BUILD -> 2800000 | C9: 0 | D9: 0 | E9: 0 | F9: 0 | G9: 0
A10: SBC 硬體 (一次性) | B10: =VX_HW_SBC -> 1200000 | C10: 0 | D10: 0 | E10: 0 | F10: 0 | G10: 0
A11: OPEN/NAS 整合工時 (一次性) | B11: =VX_INTEG -> 600000 | C11: 0 | D11: 0 | E11: 0 | F11: 0 | G11: 0
A12: 瑛聲年度維護 L1+L2 | B12: 0 | C12: =VX_MAINT*0.5 -> 900000 | D12: =VX_MAINT*(1+INFL_LABOR) -> 1854000 | E12: =D12*(1+INFL_LABOR) -> 1909620 | F12: =E12*(1+INFL_LABOR) -> 1966908.6 | G12: =F12*(1+INFL_LABOR) -> 2025915.9
A13: 硬體年度維護 (15%) | B13: 0 | C13: 0 | D13: =B10*0.15 -> 180000 | E13: =D13*(1+INFL_LICENSE) -> 183600 | F13: =E13*(1+INFL_LICENSE) -> 187272 | G13: =F13*(1+INFL_LICENSE) -> 191017.44
A14: 小計 (NTD) | B14: =SUM(B5:B13) -> 6550000 | C14: =SUM(C5:C13) -> 1662500 | D14: =SUM(D5:D13) -> 2811750 | E14: =SUM(E5:E13) -> 2886525 | F14: =SUM(F5:F13) -> 2963351.7 | G14: =SUM(G5:G13) -> 3042287.8
A15: 累積 TCO (NTD) | B15: =B14 -> 6550000 | C15: =B15+C14 -> 8212500 | D15: =C15+D14 -> 11024250 | E15: =D15+E14 -> 13910775 | F15: =E15+F14 -> 16874127 | G15: =F15+G14 -> 19916415
A17: 3 年 TCO (Y0-Y3) | B17: =B14+C14+D14+E14 -> 13910775
A18: 5 年 TCO (Y0-Y5) | B18: =SUM(B14:G14) -> 19916415
A19: 每席年成本 (5 年平均, NTD) | B19: =B18/SEATS/_YR5 -> 8851.7398
A22: 【方案 C 優勢】
A23: 1. Y0 投資相對溫和,Y1 即可 Go-live (對齊 Genesys 11/01 EOL)
A24: 2. Hybrid 授權給予「核心穩定 + 彈性擴充」的雙重彈性
A25: 3. Source Code Escrow 解決 vendor lock-in 顧慮
A26: 4. 瑛聲 Premium Partner 提供單點責任,玉山不需管多 vendor
A27: 5. 5 年 TCO 是三方案中最低,且風險最小

Sheet 對照總表
A1: 三方案對照總表 (NTD)
A2: 所有數字皆動態連結各方案工作表 — 修改假設參數會自動重算
A4: 方案 | B4: Y0 | C4: Y1 | D4: Y2 | E4: Y3 | F4: Y4 | G4: Y5 | H4: 5 年 TCO
A5: 方案 A: 續用 Genesys | B5: ='A.續用Genesys'!B10 -> 8125000 | C5: ='A.續用Genesys'!C10 -> 45905000 | D5: ='A.續用Genesys'!D10 -> 28736100 | E5: ='A.續用Genesys'!E10 -> 29403300 | F5: ='A.續用Genesys'!F10 -> 30118674 | G5: ='A.續用Genesys'!G10 -> 30852175 | H5: =SUM(B5:G5) -> 1.7314025e+08
A6: 方案 B: 自建 PBX | B6: ='B.自建'!B12 -> 2000000 | C6: ='B.自建'!C12 -> 8354200 | D6: ='B.自建'!D12 -> 14733864 | E6: ='B.自建'!E12 -> 5614140 | F6: ='B.自建'!F12 -> 5775862.8 | G6: ='B.自建'!G12 -> 5942303.3 | H6: =SUM(B6:G6) -> 42420370
A7: 方案 C: VOXEN+3CX (推薦) | B7: ='C.VOXEN+3CX'!B14 -> 6550000 | C7: ='C.VOXEN+3CX'!C14 -> 1662500 | D7: ='C.VOXEN+3CX'!D14 -> 2811750 | E7: ='C.VOXEN+3CX'!E14 -> 2886525 | F7: ='C.VOXEN+3CX'!F14 -> 2963351.7 | G7: ='C.VOXEN+3CX'!G14 -> 3042287.8 | H7: =SUM(B7:G7) -> 19916415
A9: Δ vs 方案 C (省 / 多花) | B9: =B5-B7 -> 1575000 | C9: =C5-C7 -> 44242500 | D9: =D5-D7 -> 25924350 | E9: =E5-E7 -> 26516775 | F9: =F5-F7 -> 27155322 | G9: =G5-G7 -> 27809887 | H9: =H5-H7 -> 1.5322383e+08
A10: Δ vs 方案 C (B - C) | B10: =B6-B7 -> -4550000 | C10: =C6-C7 -> 6691700 | D10: =D6-D7 -> 11922114 | E10: =E6-E7 -> 2727615 | F10: =F6-F7 -> 2812511.1 | G10: =G6-G7 -> 2900015.4 | H10: =H6-H7 -> 22503956
A13: 【結論摘要】
A14: • 方案 C (VOXEN+3CX) 在 5 年 TCO 為三方案中最低,且風險最小
A15: • 方案 A (續 Genesys) 短期看似最低,但 Y3 強迫升級會帶入新成本與遷移風險
A16: • 方案 B (自建) 帳面看起來能省授權費,但開發 + 維運 + 風險加總後通常 2-3 倍於 C
A17: • 玉山真正在意的不只是「總價」,還有「不可預期支出的風險」— 方案 C 的 buffer 與保險(Escrow)最完整
A19: 【務必告知玉山】此試算為瑛聲內部預估,所有數字假設均可調整,正式報價以 NDA 後合約為準。

Sheet 敏感性分析
A1: 敏感性分析 — 方案 C 在不同假設下的 5 年 TCO
A2: 提供玉山做議價場景的「what-if」分析:座席數、授權單價、人月費率變動會如何影響 TCO
A4: 情境 | B4: 參數變動 | C4: 5 年 TCO (預估 NTD) | D4: 對基準的差額 | E4: Δ %
A5: 基準情境 | B5: 依工作表「假設與參數」所設 | C5: ='C.VOXEN+3CX'!B18 -> 19916415 | D5: =0 -> 0 | E5: =0% -> 0
A6: 座席擴增 +20% (540 席) | B6: SEATS × 1.2 | C6: ='C.VOXEN+3CX'!B18*1.15 -> 22903877 | D6: =C6-C5 -> 2987462.2 | E6: =(C6-C5)/C5 -> 0.15
A7: 座席收縮 -20% (360 席) | B7: SEATS × 0.8 | C7: ='C.VOXEN+3CX'!B18*0.85 -> 16928952 | D7: =C7-C5 -> -2987462.2 | E7: =(C7-C5)/C5 -> -0.15
A8: License 通膨 +50% (年增 3%) | B8: INFL_LICENSE × 1.5 | C8: ='C.VOXEN+3CX'!B18*1.06 -> 21111399 | D8: =C8-C5 -> 1194984.9 | E8: =(C8-C5)/C5 -> 0.06
A9: 人月費率 +20% (台幣升值/通膨) | B9: BUILD_RATE × 1.2 | C9: ='C.VOXEN+3CX'!B18*1.08 -> 21509728 | D9: =C9-C5 -> 1593313.2 | E9: =(C9-C5)/C5 -> 0.08
A10: Escrow 高階方案 (+200K/年) | B10: + NTD 200K/年 × 5 | C10: ='C.VOXEN+3CX'!B18+1000000 -> 20916415 | D10: =C10-C5 -> 1000000 | E10: =(C10-C5)/C5 -> 0.050209841
A11: 提前退場 (Y3 終止合約) | B11: 只算 Y0-Y3 + 90天過渡 | C11: ='C.VOXEN+3CX'!B17+1500000 -> 15410775 | D11: =C11-C5 -> -4505639.5 | E11: =(C11-C5)/C5 -> -0.22622744
A15: 【說明】上述敏感性分析使用簡化倍率,精確計算需展開到子項目層級。本表用於議價場景的「快速估算」。
